pic_standard/__init__.py
pic_standard/cli.py
pic_standard/config.py
pic_standard/errors.py
pic_standard/evidence.py
pic_standard/policy.py
pic_standard/verifier.py
pic_standard/integrations/__init__.py
pic_standard/integrations/langgraph_pic_toolnode.py
pic_standard/integrations/mcp_pic_guard.py
pic_standard/schemas/proposal_schema.json
pic_standard-0.3.2.dist-info/licenses/LICENSE
pic_standard-0.3.2.dist-info/METADATA
pic_standard-0.3.2.dist-info/WHEEL
pic_standard-0.3.2.dist-info/entry_points.txt
pic_standard-0.3.2.dist-info/top_level.txt
pic_standard-0.3.2.dist-info/RECORD
