Metadata-Version: 2.4
Name: pic-standard
Version: 0.3.2
Summary: PIC Standard: Provenance & Intent Contracts for agentic side-effect governance
Author: Fabio Marcello Salvadori
License:                                  Apache License
Project-URL: Homepage, https://github.com/madeinplutofabio/pic-standard
Project-URL: Repository, https://github.com/madeinplutofabio/pic-standard
Project-URL: Issues, https://github.com/madeinplutofabio/pic-standard/issues
Requires-Python: >=3.10
License-File: LICENSE
Requires-Dist: pydantic>=2.0.0
Requires-Dist: jsonschema>=4.0.0
Provides-Extra: langgraph
Requires-Dist: langchain-core>=0.1.0; extra == "langgraph"
Dynamic: license-file
